{
  "generated_at": "2026-06-13T10:05:20.966198+00:00",
  "model": "gpt-image-2",
  "quality": "high",
  "character": "uebel (Sousou no Frieren)",
  "requests": [
    {
      "kind": "mouth",
      "attempt": 0,
      "fallback_used": false,
      "quality": "high",
      "usage": {
        "input_tokens": 1337,
        "input_tokens_details": {
          "image_tokens": 1024,
          "text_tokens": 313
        },
        "output_tokens": 7024,
        "output_tokens_details": {
          "image_tokens": 7024,
          "text_tokens": 0
        },
        "total_tokens": 8361
      },
      "estimated_usd": 0.2205,
      "out": "experiments/autorig-character-004/generated/mouth.png"
    }
  ],
  "total_estimated_usd": 0.2205
}
