{
  "part_id": "hair_back_L",
  "vertices": [
    [
      314.0,
      34.0
    ],
    [
      467.4,
      34.0
    ],
    [
      620.8,
      34.0
    ],
    [
      774.2,
      34.0
    ],
    [
      927.6,
      34.0
    ],
    [
      1081.0,
      34.0
    ],
    [
      314.0,
      420.0
    ],
    [
      467.4,
      420.0
    ],
    [
      620.8,
      420.0
    ],
    [
      774.2,
      420.0
    ],
    [
      927.6,
      420.0
    ],
    [
      1081.0,
      420.0
    ],
    [
      314.0,
      806.0
    ],
    [
      467.4,
      806.0
    ],
    [
      620.8,
      806.0
    ],
    [
      774.2,
      806.0
    ],
    [
      927.6,
      806.0
    ],
    [
      1081.0,
      806.0
    ],
    [
      314.0,
      1192.0
    ],
    [
      467.4,
      1192.0
    ],
    [
      620.8,
      1192.0
    ],
    [
      774.2,
      1192.0
    ],
    [
      927.6,
      1192.0
    ],
    [
      1081.0,
      1192.0
    ],
    [
      314.0,
      1578.0
    ],
    [
      467.4,
      1578.0
    ],
    [
      620.8,
      1578.0
    ],
    [
      774.2,
      1578.0
    ],
    [
      927.6,
      1578.0
    ],
    [
      1081.0,
      1578.0
    ],
    [
      314.0,
      1964.0
    ],
    [
      467.4,
      1964.0
    ],
    [
      620.8,
      1964.0
    ],
    [
      774.2,
      1964.0
    ],
    [
      927.6,
      1964.0
    ],
    [
      1081.0,
      1964.0
    ]
  ],
  "triangles": [
    [
      2,
      7,
      8
    ],
    [
      2,
      8,
      3
    ],
    [
      3,
      8,
      9
    ],
    [
      3,
      9,
      4
    ],
    [
      4,
      9,
      10
    ],
    [
      4,
      10,
      5
    ],
    [
      5,
      10,
      11
    ],
    [
      7,
      13,
      8
    ],
    [
      8,
      13,
      14
    ],
    [
      8,
      14,
      9
    ],
    [
      9,
      14,
      15
    ],
    [
      9,
      15,
      10
    ],
    [
      10,
      15,
      16
    ],
    [
      10,
      16,
      11
    ],
    [
      11,
      16,
      17
    ],
    [
      12,
      18,
      13
    ],
    [
      13,
      18,
      19
    ],
    [
      13,
      19,
      14
    ],
    [
      14,
      19,
      20
    ],
    [
      14,
      20,
      15
    ],
    [
      15,
      20,
      21
    ],
    [
      15,
      21,
      16
    ],
    [
      16,
      21,
      22
    ],
    [
      16,
      22,
      17
    ],
    [
      17,
      22,
      23
    ],
    [
      18,
      24,
      19
    ],
    [
      19,
      24,
      25
    ],
    [
      19,
      25,
      20
    ],
    [
      20,
      25,
      26
    ],
    [
      20,
      26,
      21
    ],
    [
      21,
      26,
      27
    ],
    [
      21,
      27,
      22
    ],
    [
      22,
      27,
      28
    ],
    [
      22,
      28,
      23
    ],
    [
      23,
      28,
      29
    ],
    [
      24,
      30,
      25
    ],
    [
      25,
      30,
      31
    ],
    [
      25,
      31,
      26
    ],
    [
      26,
      31,
      32
    ],
    [
      26,
      32,
      27
    ],
    [
      27,
      32,
      33
    ],
    [
      27,
      33,
      28
    ],
    [
      28,
      33,
      34
    ],
    [
      28,
      34,
      29
    ],
    [
      29,
      34,
      35
    ]
  ],
  "uvs": [
    [
      0.15332,
      0.016602
    ],
    [
      0.228223,
      0.016602
    ],
    [
      0.303125,
      0.016602
    ],
    [
      0.378027,
      0.016602
    ],
    [
      0.45293,
      0.016602
    ],
    [
      0.527832,
      0.016602
    ],
    [
      0.15332,
      0.205078
    ],
    [
      0.228223,
      0.205078
    ],
    [
      0.303125,
      0.205078
    ],
    [
      0.378027,
      0.205078
    ],
    [
      0.45293,
      0.205078
    ],
    [
      0.527832,
      0.205078
    ],
    [
      0.15332,
      0.393555
    ],
    [
      0.228223,
      0.393555
    ],
    [
      0.303125,
      0.393555
    ],
    [
      0.378027,
      0.393555
    ],
    [
      0.45293,
      0.393555
    ],
    [
      0.527832,
      0.393555
    ],
    [
      0.15332,
      0.582031
    ],
    [
      0.228223,
      0.582031
    ],
    [
      0.303125,
      0.582031
    ],
    [
      0.378027,
      0.582031
    ],
    [
      0.45293,
      0.582031
    ],
    [
      0.527832,
      0.582031
    ],
    [
      0.15332,
      0.770508
    ],
    [
      0.228223,
      0.770508
    ],
    [
      0.303125,
      0.770508
    ],
    [
      0.378027,
      0.770508
    ],
    [
      0.45293,
      0.770508
    ],
    [
      0.527832,
      0.770508
    ],
    [
      0.15332,
      0.958984
    ],
    [
      0.228223,
      0.958984
    ],
    [
      0.303125,
      0.958984
    ],
    [
      0.378027,
      0.958984
    ],
    [
      0.45293,
      0.958984
    ],
    [
      0.527832,
      0.958984
    ]
  ],
  "mesh_path": "meshes/hair_back_L.json"
}
